src/rtl/config_blk_final/ctrl_dram_req.v
module ctrl_dram_req #(
    parameter  addr_w=32,
    parameter burst_len_width=8
  )(
    input clkin,
    input user_start,
    input status,
    input [31:0] global_reg_address_start,
    input [31:0] global_reg_address_stop,
    output read_req,
    output valid,
    output [7:0]o_address,
    output last,
    output [burst_len_width-1:0]burst_len
  );
  reg[5:0] counter1=0;
  reg [7:0] o_address_reg=0;
  reg dv;
  reg read_req_reg;
  reg last_reg=0;
  reg [burst_len_width-1:0]burst_len_reg=0;
  reg [3:0]state=0;
  reg [31:0]internal_reg_start=0;
  reg [31:0]internal_reg_stop=0;

  always @(posedge clkin)
  begin
    case(state)
      4'd0:
      begin
        if(user_start)begin
            state<=1;
            internal_reg_start<=global_reg_address_start;
            internal_reg_stop<=global_reg_address_stop;
        end
        else
            state<=0;

      end
      4'd1:
      begin
        //idle state
        if(~status)
        begin
          read_req_reg<=1'b0;
          dv<=1'b0;
          o_address_reg<=0;
          last_reg<=0;
          burst_len_reg<=0;
          state<=4'd1;
        end
        else
          state<=4'd2;
      end
      4'd2:
      begin
        //send address to mem controller in 8bits with required signals
        o_address_reg<=internal_reg_start[addr_w-counter1-1-:8];
        counter1<=counter1+8;
        dv<=1'b1;
        read_req_reg<=1'b1;
        burst_len_reg<=7'd7;
        if(counter1==24)
        begin
          last_reg<=1'b1;
        end
        else
        begin
          last_reg<=1'b0;
        end

        if(counter1<32)
        begin
          state<=4'd2;
        end
        else
        begin
          state<=4'd3;
          dv<=1'b0;
          read_req_reg<=1'b0;
          last_reg<=1'b0;
          o_address_reg<=8'd0;
          counter1<=6'd0;
        end
      end
      4'd3:
      begin
        if((internal_reg_stop-(burst_len<<5))>internal_reg_start)
        begin
          internal_reg_start<=internal_reg_start+(burst_len_reg<<5);
          state<=4'd2;
        end
        else
        begin
          burst_len_reg=(global_reg_address_stop-internal_reg_start)>>5;
          state<=4'd4;
        end
      end
      4'd4:
      begin
        burst_len_reg<=8'd0;
        state<=4'd0;
      end
      default: begin
        read_req_reg<=1'b0;
        dv<=1'b0;
        o_address_reg<=0;
        last_reg<=0;
        burst_len_reg<=0;
        state<=0;
      end
    endcase
  end
  assign burst_len=burst_len_reg;
  assign last= last_reg;
  assign o_address=o_address_reg;
  assign valid=dv;
  assign read_req=read_req_reg;
endmodule

src/rtl/config_blk_final/inst_read_ctrl.v
module inst_read_ctrl(
    input clkin,
    //input [3:0]opcode,//from busmaster
    //input [7:0]prev_sent_reg,//from status reg(i think)
    input status_inst_q,//status of I.Q
    input user_start,//not sure what it does yet
    input done_status,

    ////set next status reg
    //output reg [3:0]ack_set_status,//set ack reg 1
    output read_signal// read IQ
    //output reg start_signal_inst,//for status
    //output reg bus_master_valid //for bus master idc
  );
  reg read_signal_reg;
  reg [3:0]top_state=4'd0;
  
  //reg [7:0]prev_sent;
  //reg [7:0]next_sent=8'b0;

  always @(posedge clkin)
  begin
    case(top_state)
    4'd0:begin
      if(user_start)begin
        top_state<=4'd1;//shift to nonidle state
      end
      else
        top_state<=4'd0;
    end
    4'd1:begin
      if(status_inst_q)
    begin
      if(done_status)
      begin
        read_signal_reg<=1'b1;
      end
      else
      begin
        read_signal_reg<=1'b0;
      end
    end
    end    
    endcase
  end
  assign read_signal=read_signal_reg;
  //assign next_status_reg=next_sent;

endmodule

src/rtl/config_blk_final/ctrl_ack.v
module ctrl_ack(
    input clkin,
    input inst_1,
    input inst_2,
    input inst_3,
    input inst_4,
    input inst_1_valid,
    input inst_2_valid,
    input inst_3_valid,
    input inst_4_valid,
    output reg [3:0]status_ack,
    output reg [7:0]status_prev,
    output reg [3:0]o_valid_sig
);
always@(posedge clkin)begin
    if(inst_1&inst_1_valid)begin
        status_ack[0]<=0;
        status_prev[1:0]<=2'b11;
        o_valid_sig[0]<=1'b1;
    end
    else
        o_valid_sig[0]<=1'b0;
    if(inst_2&inst_2_valid)begin
        status_ack[1]<=0;
        status_prev[3:2]<=2'b11;
        o_valid_sig[1]<=1'b1;
    end
    else
        o_valid_sig[1]<=1'b0;
    if(inst_3&inst_3_valid)begin
        status_ack[2]<=0;
        status_prev[5:4]<=2'b11;
        o_valid_sig[2]<=1'b1;
    end
    else
        o_valid_sig[2]<=1'b0;
    if(inst_4&inst_4_valid)begin
        status_ack[3]<=0;
        status_prev[7:6]<=2'b11;
        o_valid_sig[3]<=1'b1;
    end
    else
        o_valid_sig[3]<=1'b0;
end
endmodule

src/rtl/config_blk_final/status_reg.v
module status_reg#(
    parameter inst_num=8'd4
  )(
    input clkin,
    input [3:0]opcode,//from busmaster

    input [7:0]prev_in,//from ctrlack
    input [inst_num-1:0]ack_in,//from ctrlack
    input [3:0]valid_ack,//from ctrlack valid signal
    input opcode_valid,
    //input [5:0]total_layer,//from top

    //input [7:0]next_reg_update,//from inst_red_ctrl to set next as 01
    //input [3:0]ack_set, //from inst_read_ctrl for setting ack 1
    //input start_signal,//from bus master //actually from isnt ctrl after opcode 1111(mar 16)

    output [7:0]prev_out,
    output [inst_num-1:0]ack_sig,
    output [7:0]next_out,
    output reg bus_master_valid
  );
  //reg [5:0]layer_number=6'd0;
  reg [(inst_num<<1)-1:0]prev_sent=0;// [7:0] prev_sent
  reg [(inst_num<<1)-1:0]next_sent=0;// [7:0] next_sent
  reg [inst_num-1:0]ack_reg=0;
  reg [3:0]statelayer=4'd0;
  reg [3:0]new_state=4'd0;
  reg [3:0]state0=4'd0;
  reg [3:0]state1=4'd0;
  reg [3:0]state2=4'd0;
  reg [3:0]state3=4'd0;
  reg [3:0]state4=4'd0;

  // opcode 0,1,2,3 for respective registers in prev next
  always @(posedge clkin)
  begin
    //resetting ack based on ctrl ackz

    if(valid_ack[0])
    begin
      prev_sent[1:0]<=prev_in[1:0]; // makes prev 11
      ack_reg[0]<=ack_in[0]; // makes ack 0
    end
    if(valid_ack[1])
    begin
      prev_sent[3:2]<=prev_in[3:2];
      ack_reg[1]<=ack_in[1];
    end

    if(valid_ack[2])
    begin
      prev_sent[5:4]<=prev_in[5:4];
      ack_reg[2]<=ack_in[2];
    end

    if(valid_ack[3])
    begin
      prev_sent[7:6]<=prev_in[7:6];
      ack_reg[3]<=ack_in[3];
    end

    if(opcode_valid)
    begin
      if(opcode==4'd0)
      begin
        //ack_set_status[0]<=1'b1;
        case(state0)
          4'b0:
          begin
            if(prev_sent[1:0]==2'b00)
            begin
              state0<=1;
              bus_master_valid<=1'b0;
            end
            else if(prev_sent[1:0]==2'b01)
            begin
              state0<=2;
              bus_master_valid<=1'b0;
            end
            else if(prev_sent[1:0]==2'b11)
            begin
              state0<=3;
              bus_master_valid<=1'b0;
            end
          end
          4'd1:
          begin
            next_sent[1:0]<=2'b01;
            bus_master_valid<=1'b1;//send to bus to give green light to bus_master
            state0<=4'd0;
          end
          4'd2:
          begin
            if(prev_sent[1:0]==2'b11)
            begin
              state0<=3;
            end
            else
              state0<=2;
          end
          4'd3:
          begin
            next_sent[1:0]<=2'b01;
            bus_master_valid<=1'b1;
            state0<=4'd0;
          end

        endcase
      end
      /* else
      begin
        ack_set_status[0]=1'b0;
      end */
      if(opcode==4'd1)
      begin
        //ack_set_status[1]<=1'b1;
        case(state2)
          4'b0:
          begin
            if(prev_sent[3:2]==2'b00)
            begin
              state2<=1;
              bus_master_valid<=1'b0;
            end
            else if(prev_sent[3:2]==2'b01)
            begin
              state2<=2;
              bus_master_valid<=1'b0;
            end
            else if(prev_sent[3:2]==2'b11)
            begin
              state2<=3;
              bus_master_valid<=1'b0;
            end
          end
          4'd1:
          begin
            next_sent[3:2]<=2'b01;
            bus_master_valid<=1'b1;
            state2<=4'd0;
          end
          4'd2:
          begin
            if(prev_sent[3:2]==2'b11)
            begin
              state2<=3;
            end
            else
              state2<=2;
          end
          4'd3:
          begin
            next_sent[3:2]<=2'b01;
            bus_master_valid<=1'b1;
            state2<=4'd0;
          end

        endcase
      end
      /* else
      begin
        ack_set_status[1]=1'b0;
      end */
      if(opcode==4'd2)
      begin
        //ack_set_status[2]<=1'b1;
        case(state3)
          4'b0:
          begin
            if(prev_sent[5:4]==2'b00)
            begin
              state3<=1;
              bus_master_valid<=1'b0;
            end
            else if(prev_sent[5:4]==2'b01)
            begin
              state3<=2;
              bus_master_valid<=1'b0;
            end
            else if(prev_sent[5:4]==2'b11)
            begin
              state3<=3;
              bus_master_valid<=1'b0;
            end
          end
          4'd1:
          begin
            next_sent[5:4]<=2'b01;
            bus_master_valid<=1'b1;
            state3<=4'd0;
          end
          4'd2:
          begin
            if(prev_sent[5:4]==2'b11)
            begin
              state3<=3;
            end
            else
              state3<=2;
          end
          4'd3:
          begin
            next_sent[5:4]<=2'b01;
            bus_master_valid<=1'b1;
            state3<=4'd0;
          end

        endcase
      end
      /* else
      begin
        ack_set_status[2]=1'b0;
      end */
      if(opcode==4'd3)
      begin
        //ack_set_status[3]<=1'b1;
        case(state4)
          4'b0:
          begin
            if(prev_sent[7:6]==2'b00)
            begin
              state4<=1;
              bus_master_valid<=1'b0;
            end
            else if(prev_sent[7:6]==2'b01)
            begin
              state4<=2;
              bus_master_valid<=1'b0;
            end
            else if(prev_sent[7:6]==2'b11)
            begin
              state4<=3;
              bus_master_valid<=1'b0;
            end
          end
          4'd1:
          begin
            next_sent[7:6]<=2'b01;
            bus_master_valid<=1'b1;
            state4<=4'd0;
          end
          4'd2:
          begin
            if(prev_sent[7:6]==2'b11)
            begin
              state4<=3;
            end
            else
              state4<=2;
          end
          4'd3:
          begin
            next_sent[7:6]<=2'b01;
            bus_master_valid<=1'b1;
            state4<=4'd0;
          end
        endcase

      end
      if(opcode==4'b1111)
      begin
        if(ack_reg==4'b0000)
        begin
          prev_sent<=next_sent;
          bus_master_valid<=1'b1;
          if(next_sent[1:0]==2'b01)
          begin
            ack_reg[0]<=1'b1;
          end
          if(next_sent[3:2]==2'b01)
          begin
            ack_reg[1]<=1'b1;
          end
          if(next_sent[5:4]==2'b01)
          begin
            ack_reg[2]<=1'b1;
          end
          if(next_sent[7:6]==2'b01)
          begin
            ack_reg[3]<=1'b1;
          end
        end
        else
        begin
          bus_master_valid<=1'b0;
        end
      end
    end
  end
  assign ack_sig=ack_reg;
  assign prev_out=prev_sent;
  assign next_out=next_sent;
endmodule

src/rtl/config_blk_final/bus_master_fake.v
module bus_master_fake(
    input clkin,
    input [255:0]instruction_from_q,
    //input start_trigger,//when one send latched instruction to blocks in 8 bits
    input bus_master_valid,//from status reg
    output done_status,
    output reg ack_im2col,
    output reg ack_im2col_valid,
    output reg ack_tail,
    output reg ack_tail_valid,
    output reg [3:0]opcode,
    output reg opcode_valid,
    output reg start_blocks
  );
  reg done_status_reg=1'b1;
  reg [255:0]latched_instruction;
  reg [29:0]counter=30'd0;
  reg [3:0]state1=4'd0;
  always @(posedge clkin)
  begin
    case(state1)
      4'd0:
      begin
        if(instruction_from_q==256'd123456)
        begin
          state1<=4'd1;
          //start_signal<=1'b0;
          latched_instruction<=instruction_from_q;
          ack_im2col<=1'b0;
          ack_im2col_valid=1'b0;
          done_status_reg<=1'b1;
          start_blocks<=1'b0;
        end
        else if (instruction_from_q==256'd234567)
        begin
          latched_instruction<=instruction_from_q;
          ack_tail<=1'b0;
          ack_tail_valid=1'b0;
          done_status_reg<=1'b1;
          state1<=4'd1;
        end
        else if (instruction_from_q==256'd111111)
        begin
          latched_instruction<=instruction_from_q;
          /* ack_tail<=1'b0;
          ack_tail_valid=1'b0; */
          done_status_reg<=1'b1;
          state1<=4'd1;
        end
        else
          state1<=4'd0;
      end
      4'd1:
      begin
        if(counter<30'd50)
        begin
          opcode_valid=1'b0;
          counter<=counter+1;
          done_status_reg<=1'b0;
          case(latched_instruction)
            256'd123456:
              opcode<=4'd0;
            256'd234567:
              opcode<=4'd1;
            256'd111111:
              opcode<=4'b1111;
          endcase
        end
        else
        begin
          state1<=4'd2;
          opcode_valid=1'b1;
        end
      end
      4'd2:begin
        if(bus_master_valid)begin
          opcode_valid=1'b0;
          counter<=30'd0;
          done_status_reg<=1'b1;
          state1<=1'b0;

          case(latched_instruction)
            256'd123456:
            begin
              ack_im2col<=1'b1;
              ack_im2col_valid=1'b1;
            end
            256'd234567:
            begin
              ack_tail<=1'b1;
              ack_tail_valid=1'b1;
            end
            256'd111111:
            begin
              start_blocks<=1'b1;
            end
          endcase
        end
        else
          begin
            state1<=4'd2;
            done_status_reg<=1'b0;
            ack_tail<=1'b0;
            ack_tail_valid=1'b0;
            ack_im2col<=1'b0;
            ack_im2col_valid=1'b0;
            start_blocks<=1'b0;
            opcode_valid=1'b1;
          end
      end
    endcase
  end
  assign done_status=done_status_reg;
endmodule

src/rtl/config_blk_final/sync_fifo_config.v
module synchronous_fifo #(parameter DEPTH=100, DATA_WIDTH=256) (
    input clk, rst_n,
    input w_en, r_en,
    input [DATA_WIDTH-1:0] data_in,
    output reg [DATA_WIDTH-1:0] data_out,
    output full, empty,
    output [8:0]occupants,
    output ten_trigg,
    output not_empty
  );

  reg [5:0] w_ptr=1'b0;
  reg [5:0] r_ptr=1'b0;
  reg [DATA_WIDTH-1:0] fifo[DEPTH:0];
  reg [8:0]occupants_reg=1'b0;
  reg [3:0]whatever;
  // Set Default values on reset.
  always@(posedge clk)
  begin
    if(!rst_n)
    begin
      w_ptr <= 0;
      r_ptr <= 0;
      data_out <= 0;
      occupants_reg<=0;
    end

    // To write data to FIFO
    else
    begin
      if(w_en & !full)
      begin
        fifo[w_ptr] <= data_in;
        w_ptr <= w_ptr + 1;
      end

      // To read data from FIFO
      if(r_en & !empty)
      begin
        data_out <= fifo[r_ptr];
        r_ptr <= r_ptr + 1;
      end
      whatever<=(w_en&&!full)+(r_en&&!empty);
      case(whatever)
        2'd0:
          occupants_reg<=occupants_reg;
        2'd1:
        begin
          if(w_en)
          begin
            occupants_reg<=occupants_reg+1;
          end
          else
          begin
            occupants_reg<=occupants_reg-1;
          end
        end
        2'd2:
          occupants_reg<=occupants_reg;
      endcase
    end
  end


  assign occupants=occupants_reg;
  assign full = ((w_ptr+1'b1) == r_ptr);
  assign empty = (w_ptr == r_ptr);
  assign ten_trigg=(occupants<10);
  assign not_empty=~(w_ptr == r_ptr);
endmodule

src/rtl/config_blk_final/inst_q.v
`include "sync_fifo_config.v"
module instruct_q(
    input clkin,
    input [255:0]instruct_mem,
    input read_req_inst,
    input instruct_valid,
    output [255:0]o_instruction,
    output o_status_dram,
    output o_status_inst
);
synchronous_fifo  instant(.clk(clkin),.rst_n(1'b1),.w_en(instruct_valid),.r_en(read_req_inst),.data_in(instruct_mem),.data_out(o_instruction),.full(),.empty(),.ten_trigg(o_status_dram),.not_empty(o_status_inst));
endmodule

src/rtl/config_blk_final/controller_inst_q.v
module controller_inst_q(
    input clkin,
    input valid,
    input sel,
    input [255:0]i_instruction_data,
    output reg [255:0]o_instruction,
    output reg o_instruction_valid
  );
  reg [255:0]internal_reg=0;
  always@(posedge clkin)
  begin
    if(sel)
    begin
      if(valid)
      begin
//        internal_reg<=i_instruction_data;
        o_instruction<=i_instruction_data;
        o_instruction_valid<=1;
      end
      else
        begin
          o_instruction_valid<=0;
        end
    end
    else
      begin
        o_instruction_valid<=0;
        o_instruction<=256'd0;
      end
  end
  endmodule

src/rtl/config_blk_final/top_mod.v
`include "controller_inst_q.v"
`include "ctrl_ack.v"
`include "ctrl_dram_req.v"
`include "inst_read_ctrl.v"
`include "inst_q.v"
`include "status_reg.v"
`include "bus_master_fake.v"

module top_mod(
    input clkin,
    input user_start,
    input ctrl_q_valid,
    input ctrl_q_sel,
    input [255:0]instruction_data,
    input [31:0]global_start,
    input [31:0]global_stop,
    output memory_read_r,memory_valid,
    output [7:0]mem_address,
    output mem_last,
    output [7:0]mem_burst_len

  );
  wire [255:0]instruct_q_in;
  wire queue_valid;
  wire req_inst_q;
  controller_inst_q control_q(.clkin(clkin),.valid(ctrl_q_valid),.sel(ctrl_q_sel),.i_instruction_data(instruction_data),.o_instruction(instruct_q_in),.o_instruction_valid(queue_valid));

  wire [255:0]master_bus_ins;
  wire o_status_dram,o_status_inst;
  instruct_q queue(.clkin(clkin),.instruct_mem(instruct_q_in),.read_req_inst(req_inst_q),.instruct_valid(queue_valid),.o_instruction(master_bus_ins),.o_status_dram(o_status_dram),.o_status_inst(o_status_inst));

  wire [3:0]opcode_bus_master;
  wire bus_start;
  wire done_bus_master;
  wire inst_1, inst_1_valid;
  wire inst_2, inst_2_valid;
  wire bus_master_valid;
  wire opcode_valid;
  bus_master_fake bus_master(.clkin(clkin),.instruction_from_q(master_bus_ins),.opcode_valid(opcode_valid),.bus_master_valid(bus_master_valid),.done_status(done_bus_master),.ack_im2col(inst_1),.ack_im2col_valid(inst_1_valid),.ack_tail(inst_2),.ack_tail_valid(inst_2_valid),.opcode(opcode_bus_master),.start_blocks());
  status_reg status_block(.clkin(clkin),.opcode(opcode_bus_master),.opcode_valid(opcode_valid),.prev_in(prev_in_ack),.ack_in(ack_in_ack),.valid_ack(valid_ack_ack),.prev_out(),.ack_sig(),.next_out(),.bus_master_valid(bus_master_valid));
  ctrl_ack control_ack(.clkin(clkin),.inst_2(inst_2),.inst_1(inst_1),.inst_3(),.inst_4(),.inst_2_valid(inst_2_valid),.inst_1_valid(inst_1_valid),.inst_3_valid(),.inst_4_valid(),.status_ack(ack_in_ack),.status_prev(prev_in_ack),.o_valid_sig(valid_ack_ack));


  //wire [3:0]ack_set_status;
  wire [7:0]prev_in_ack;
  wire [3:0]ack_in_ack;
  wire [3:0]valid_ack_ack;
  //wire [7:0]prev_sent_display;
  //wire [7:0]next_status_reg;

  inst_read_ctrl read_inst(
                   .clkin(clkin),
                   .status_inst_q(o_status_inst),
                   .user_start(user_start),
                   .done_status(done_bus_master),
                   .read_signal(req_inst_q)
                 );
  ctrl_dram_req control_the_dram(.clkin(clkin),.user_start(user_start),.status(o_status_dram),.global_reg_address_start(global_start),.global_reg_address_stop(global_stop),.read_req(memory_read_r),.valid(memory_valid),.o_address(mem_address),.last(mem_last),.burst_len(mem_burst_len));
endmodule

src/rtl/config_blk_final/top_mod_tb.v
`include "top_mod.v"
`timescale 1ns/1ps

module top_mod_tb();
reg clkin=1'b0;
reg user_start;
reg ctrl_q_valid;
reg ctrl_q_sel;
reg bus_start;
reg [5:0]total_layer_1;
reg [31:0]global_start;
reg [31:0]global_stop;
reg [255:0]instruction_data;
wire memory_read_r;
wire memory_valid;
wire [7:0]mem_address;
wire mem_last;
wire [7:0]mem_burst_len;
wire [3:0]ack_sig;
wire [7:0]next_out;

always #5 clkin=~clkin;
top_mod AAAAAAAAAAAAH(.clkin(clkin),
.user_start(user_start),
.ctrl_q_valid(ctrl_q_valid),
.ctrl_q_sel(ctrl_q_sel),
.global_start(global_start),
.global_stop(global_stop),
.instruction_data(instruction_data),
.memory_read_r(memory_read_r),
.memory_valid(memory_valid),
.mem_address(mem_address),
.mem_last(mem_last),
.mem_burst_len(mem_burst_len)
);
initial begin
instruction_data=256'd123456;
user_start=1'b0;
ctrl_q_sel=1'b0;
ctrl_q_valid=1'b0;
global_start=32'd1234;
global_stop=32'd4567;
total_layer_1=6'd10;
#10;
user_start=1'b1;
#10;
user_start=1'b0;
#40;
ctrl_q_sel=1'b1;
ctrl_q_valid=1'b1;
#30;
ctrl_q_sel=1'b0;
ctrl_q_valid=1'b0;
#820;
instruction_data=256'd234567;
ctrl_q_sel=1'b1;
ctrl_q_valid=1'b1;
#30;
ctrl_q_sel=1'b0;
ctrl_q_valid=1'b0;
#820;
ctrl_q_sel=1'b1;
ctrl_q_valid=1'b1;
instruction_data=256'd111111;
#30;
ctrl_q_sel=1'b0;
ctrl_q_valid=1'b0;
#10000;
$finish;
end
initial begin
    $dumpfile("top_mod_tb.vcd");
    $dumpvars(0);
end
endmodule

src/rtl/config_blk_final/top_mod_tb.vcd
$date
	Wed Mar 20 10:06:32 2024
$end
$version
	Icarus Verilog
$end
$timescale
	1ps
$end
$scope module top_mod_tb $end
$var wire 1 ! memory_valid $end
$var wire 1 " memory_read_r $end
$var wire 1 # mem_last $end
$var wire 8 $ mem_burst_len [7:0] $end
$var wire 8 % mem_address [7:0] $end
$var reg 1 & clkin $end
$var reg 1 ' ctrl_q_sel $end
$var reg 1 ( ctrl_q_valid $end
$var reg 32 ) global_start [31:0] $end
$var reg 32 * global_stop [31:0] $end
$var reg 256 + instruction_data [255:0] $end
$var reg 6 , total_layer_1 [5:0] $end
$var reg 1 - user_start $end
$scope module AAAAAAAAAAAAH $end
$var wire 1 & clkin $end
$var wire 1 ' ctrl_q_sel $end
$var wire 1 ( ctrl_q_valid $end
$var wire 32 . global_start [31:0] $end
$var wire 32 / global_stop [31:0] $end
$var wire 256 0 instruction_data [255:0] $end
$var wire 1 - user_start $end
$var wire 4 1 valid_ack_ack [3:0] $end
$var wire 1 2 req_inst_q $end
$var wire 1 3 queue_valid $end
$var wire 8 4 prev_in_ack [7:0] $end
$var wire 1 5 opcode_valid $end
$var wire 4 6 opcode_bus_master [3:0] $end
$var wire 1 7 o_status_inst $end
$var wire 1 8 o_status_dram $end
$var wire 1 ! memory_valid $end
$var wire 1 " memory_read_r $end
$var wire 1 # mem_last $end
$var wire 8 9 mem_burst_len [7:0] $end
$var wire 8 : mem_address [7:0] $end
$var wire 256 ; master_bus_ins [255:0] $end
$var wire 256 < instruct_q_in [255:0] $end
$var wire 1 = inst_2_valid $end
$var wire 1 > inst_2 $end
$var wire 1 ? inst_1_valid $end
$var wire 1 @ inst_1 $end
$var wire 1 A done_bus_master $end
$var wire 1 B bus_master_valid $end
$var wire 4 C ack_in_ack [3:0] $end
$scope module bus_master $end
$var wire 1 & clkin $end
$var wire 1 A done_status $end
$var wire 256 D instruction_from_q [255:0] $end
$var wire 1 B bus_master_valid $end
$var reg 1 @ ack_im2col $end
$var reg 1 ? ack_im2col_valid $end
$var reg 1 > ack_tail $end
$var reg 1 = ack_tail_valid $end
$var reg 30 E counter [29:0] $end
$var reg 1 F done_status_reg $end
$var reg 256 G latched_instruction [255:0] $end
$var reg 4 H opcode [3:0] $end
$var reg 1 5 opcode_valid $end
$var reg 1 I start_blocks $end
$var reg 4 J state1 [3:0] $end
$upscope $end
$scope module control_ack $end
$var wire 1 & clkin $end
$var wire 1 @ inst_1 $end
$var wire 1 ? inst_1_valid $end
$var wire 1 > inst_2 $end
$var wire 1 = inst_2_valid $end
$var wire 1 K inst_3 $end
$var wire 1 L inst_3_valid $end
$var wire 1 M inst_4 $end
$var wire 1 N inst_4_valid $end
$var reg 4 O o_valid_sig [3:0] $end
$var reg 4 P status_ack [3:0] $end
$var reg 8 Q status_prev [7:0] $end
$upscope $end
$scope module control_q $end
$var wire 1 & clkin $end
$var wire 256 R i_instruction_data [255:0] $end
$var wire 1 ' sel $end
$var wire 1 ( valid $end
$var reg 256 S internal_reg [255:0] $end
$var reg 256 T o_instruction [255:0] $end
$var reg 1 3 o_instruction_valid $end
$upscope $end
$scope module control_the_dram $end
$var wire 8 U burst_len [7:0] $end
$var wire 1 & clkin $end
$var wire 32 V global_reg_address_start [31:0] $end
$var wire 32 W global_reg_address_stop [31:0] $end
$var wire 1 # last $end
$var wire 8 X o_address [7:0] $end
$var wire 1 " read_req $end
$var wire 1 - user_start $end
$var wire 1 ! valid $end
$var wire 1 8 status $end
$var reg 8 Y burst_len_reg [7:0] $end
$var reg 6 Z counter1 [5:0] $end
$var reg 1 [ dv $end
$var reg 32 \ internal_reg_start [31:0] $end
$var reg 32 ] internal_reg_stop [31:0] $end
$var reg 1 ^ last_reg $end
$var reg 8 _ o_address_reg [7:0] $end
$var reg 1 ` read_req_reg $end
$var reg 4 a state [3:0] $end
$upscope $end
$scope module queue $end
$var wire 1 & clkin $end
$var wire 256 b instruct_mem [255:0] $end
$var wire 1 3 instruct_valid $end
$var wire 1 2 read_req_inst $end
$var wire 1 7 o_status_inst $end
$var wire 1 8 o_status_dram $end
$var wire 256 c o_instruction [255:0] $end
$scope module instant $end
$var wire 1 & clk $end
$var wire 256 d data_in [255:0] $end
$var wire 1 7 not_empty $end
$var wire 1 e rst_n $end
$var wire 1 3 w_en $end
$var wire 1 8 ten_trigg $end
$var wire 1 2 r_en $end
$var wire 9 f occupants [8:0] $end
$var wire 1 g full $end
$var wire 1 h empty $end
$var reg 256 i data_out [255:0] $end
$var reg 9 j occupants_reg [8:0] $end
$var reg 6 k r_ptr [5:0] $end
$var reg 6 l w_ptr [5:0] $end
$var reg 4 m whatever [3:0] $end
$upscope $end
$upscope $end
$scope module read_inst $end
$var wire 1 & clkin $end
$var wire 1 A done_status $end
$var wire 1 2 read_signal $end
$var wire 1 7 status_inst_q $end
$var wire 1 - user_start $end
$var reg 1 n read_signal_reg $end
$var reg 4 o top_state [3:0] $end
$upscope $end
$scope module status_block $end
$var wire 4 p ack_in [3:0] $end
$var wire 4 q ack_sig [3:0] $end
$var wire 1 & clkin $end
$var wire 8 r next_out [7:0] $end
$var wire 4 s opcode [3:0] $end
$var wire 1 5 opcode_valid $end
$var wire 8 t prev_in [7:0] $end
$var wire 8 u prev_out [7:0] $end
$var wire 4 v valid_ack [3:0] $end
$var reg 4 w ack_reg [3:0] $end
$var reg 1 B bus_master_valid $end
$var reg 4 x new_state [3:0] $end
$var reg 8 y next_sent [7:0] $end
$var reg 8 z prev_sent [7:0] $end
$var reg 4 { state0 [3:0] $end
$var reg 4 | state1 [3:0] $end
$var reg 4 } state2 [3:0] $end
$var reg 4 ~ state3 [3:0] $end
$var reg 4 !" state4 [3:0] $end
$var reg 4 "" statelayer [3:0] $end
$upscope $end
$upscope $end
$upscope $end
$enddefinitions $end
#0
$dumpvars
b0 ""
b0 !"
b0 ~
b0 }
b0 |
b0 {
b0 z
b0 y
b0 x
b0 w
bx v
b0 u
bx t
bx s
b0 r
b0 q
bx p
b0 o
xn
bx m
b0 l
b0 k
b0 j
bx i
1h
0g
b0 f
1e
bx d
bx c
bx b
b0 a
x`
b0 _
0^
b0 ]
b0 \
x[
b0 Z
b0 Y
b0 X
b1000111010111 W
b10011010010 V
b0 U
bx T
b0 S
b11110001001000000 R
bx Q
bx P
bx O
zN
zM
zL
zK
b0 J
xI
bx H
bx G
1F
b0 E
bx D
bx C
xB
1A
x@
x?
x>
x=
bx <
bx ;
b0 :
b0 9
18
07
bx 6
x5
bx 4
x3
x2
bx 1
b11110001001000000 0
b1000111010111 /
b10011010010 .
0-
b1010 ,
b11110001001000000 +
b1000111010111 *
b10011010010 )
0(
0'
0&
b0 %
b0 $
0#
x"
x!
$end
#5000
b0 <
b0 T
b0 b
b0 d
03
b0 1
b0 O
b0 v
1&
#10000
0&
1-
#15000
b1000111010111 ]
b10011010010 \
b1 a
b1 o
b0 m
1&
#20000
0&
0-
#25000
b10 a
1&
#30000
0&
#35000
b111 $
b111 9
b111 U
b111 Y
1"
1`
1!
1[
b1000 Z
1&
#40000
0&
#45000
b10000 Z
1&
#50000
0&
#55000
b11000 Z
b100 %
b100 :
b100 X
b100 _
1&
#60000
0&
1(
1'
#65000
13
b11110001001000000 <
b11110001001000000 T
b11110001001000000 b
b11110001001000000 d
1#
1^
b100000 Z
b11010010 %
b11010010 :
b11010010 X
b11010010 _
1&
#70000
0&
#75000
17
0"
0`
0!
0[
b11 a
0#
0^
b0 Z
b0 %
b0 :
b0 X
b0 _
b1 m
0h
b1 l
1&
#80000
0&
#85000
b1 f
b1 j
bx m
b10 l
12
1n
b10 a
b10110110010 \
1&
#90000
0&
0(
0'
#95000
1"
1`
1!
1[
b1000 Z
b10 m
b1 k
b11110001001000000 ;
b11110001001000000 D
b11110001001000000 c
b11110001001000000 i
b11 l
b0 <
b0 T
b0 b
b0 d
03
1&
#100000
0&
#105000
b1 m
b10 k
0I
0@
b11110001001000000 G
b1 J
b10000 Z
0?
1&
#110000
0&
#115000
07
b11000 Z
b101 %
b101 :
b101 X
b101 _
b0 6
b0 H
b0 s
0A
0F
b1 E
b0 f
b0 j
1h
b11 k
05
1&
#120000
0&
#125000
08
b111111111 f
b111111111 j
b0 m
b10 E
1#
1^
b100000 Z
b10110010 %
b10110010 :
b10110010 X
b10110010 _
1&
#130000
0&
#135000
0"
0`
0!
0[
b11 a
0#
0^
b0 Z
b0 %
b0 :
b0 X
b0 _
b11 E
1&
#140000
0&
#145000
b100 E
b10 a
b11010010010 \
1&
#150000
0&
#155000
1"
1`
1!
1[
b1000 Z
b101 E
1&
#160000
0&
#165000
b110 E
b10000 Z
1&
#170000
0&
#175000
b11000 Z
b110 %
b110 :
b110 X
b110 _
b111 E
1&
#180000
0&
#185000
b1000 E
1#
1^
b100000 Z
b10010010 %
b10010010 :
b10010010 X
b10010010 _
1&
#190000
0&
#195000
0"
0`
0!
0[
b11 a
0#
0^
b0 Z
b0 %
b0 :
b0 X
b0 _
b1001 E
1&
#200000
0&
#205000
b1010 E
b10 a
b11101110010 \
1&
#210000
0&
#215000
1"
1`
1!
1[
b1000 Z
b1011 E
1&
#220000
0&
#225000
b1100 E
b10000 Z
1&
#230000
0&
#235000
b11000 Z
b111 %
b111 :
b111 X
b111 _
b1101 E
1&
#240000
0&
#245000
b1110 E
1#
1^
b100000 Z
b1110010 %
b1110010 :
b1110010 X
b1110010 _
1&
#250000
0&
#255000
0"
0`
0!
0[
b11 a
0#
0^
b0 Z
b0 %
b0 :
b0 X
b0 _
b1111 E
1&
#260000
0&
#265000
b10000 E
b10 a
b100001010010 \
1&
#270000
0&
#275000
1"
1`
1!
1[
b1000 Z
b10001 E
1&
#280000
0&
#285000
b10010 E
b10000 Z
1&
#290000
0&
#295000
b11000 Z
b1000 %
b1000 :
b1000 X
b1000 _
b10011 E
1&
#300000
0&
#305000
b10100 E
1#
1^
b100000 Z
b1010010 %
b1010010 :
b1010010 X
b1010010 _
1&
#310000
0&
